{
  "_type": "export",
  "__export_format": 4,
  "__export_date": "2026-05-03T17:52:32.620663+00:00",
  "__export_source": "SmartShoppingAssistant Postman migration",
  "resources": [
    {
      "_id": "wrk_promotion-crud",
      "_type": "workspace",
      "name": "Promotion CRUD",
      "description": "Imported from Promotion CRUD.postman_collection.json",
      "scope": "collection",
      "created": 0,
      "modified": 0
    },
    {
      "_id": "env_promotion-crud",
      "_type": "environment",
      "parentId": "wrk_promotion-crud",
      "name": "Local",
      "data": {
        "baseUrl": "http://localhost:5120",
        "productId": "1",
        "categoryId": "1"
      },
      "created": 0,
      "modified": 0
    },
    {
      "_id": "grp_promotion-crud",
      "_type": "request_group",
      "parentId": "wrk_promotion-crud",
      "name": "Promotion CRUD",
      "description": "",
      "created": 0,
      "modified": 0
    },
    {
      "_id": "req_promotion-crud_01",
      "_type": "request",
      "parentId": "grp_promotion-crud",
      "name": "Get All Promotions",
      "method": "GET",
      "url": "{{baseUrl}}/api/promotion",
      "headers": [
        {
          "name": "Accept",
          "value": "application/json"
        }
      ],
      "parameters": [],
      "authentication": {},
      "body": {},
      "settingStoreCookies": true,
      "settingSendCookies": true,
      "settingDisableRenderRequestBody": false,
      "settingEncodeUrl": true,
      "settingRebuildPath": true,
      "settingFollowRedirects": "global",
      "settingRepeatDelay": 0,
      "settingMaxRedirects": 0,
      "created": 0,
      "modified": 0
    },
    {
      "_id": "req_promotion-crud_02",
      "_type": "request",
      "parentId": "grp_promotion-crud",
      "name": "Create Promotion",
      "method": "POST",
      "url": "{{baseUrl}}/api/promotion",
      "headers": [
        {
          "name": "Content-Type",
          "value": "application/json"
        },
        {
          "name": "Accept",
          "value": "application/json"
        }
      ],
      "parameters": [],
      "authentication": {},
      "body": {
        "mimeType": "application/json",
        "text": "{\n  \"name\": \"Test Promotion\",\n  \"type\": 0,\n  \"threshold\": 3,\n  \"reward\": 1,\n  \"rewardValue\": 10,\n  \"isActive\": true\n}\n"
      },
      "settingStoreCookies": true,
      "settingSendCookies": true,
      "settingDisableRenderRequestBody": false,
      "settingEncodeUrl": true,
      "settingRebuildPath": true,
      "settingFollowRedirects": "global",
      "settingRepeatDelay": 0,
      "settingMaxRedirects": 0,
      "created": 0,
      "modified": 0
    },
    {
      "_id": "req_promotion-crud_03",
      "_type": "request",
      "parentId": "grp_promotion-crud",
      "name": "Get Promotion by ID",
      "method": "GET",
      "url": "{{baseUrl}}/api/promotion/{{promotionId}}",
      "headers": [
        {
          "name": "Accept",
          "value": "application/json"
        }
      ],
      "parameters": [],
      "authentication": {},
      "body": {},
      "settingStoreCookies": true,
      "settingSendCookies": true,
      "settingDisableRenderRequestBody": false,
      "settingEncodeUrl": true,
      "settingRebuildPath": true,
      "settingFollowRedirects": "global",
      "settingRepeatDelay": 0,
      "settingMaxRedirects": 0,
      "created": 0,
      "modified": 0
    },
    {
      "_id": "req_promotion-crud_04",
      "_type": "request",
      "parentId": "grp_promotion-crud",
      "name": "Update Promotion",
      "method": "PUT",
      "url": "{{baseUrl}}/api/promotion/{{promotionId}}",
      "headers": [
        {
          "name": "Content-Type",
          "value": "application/json"
        },
        {
          "name": "Accept",
          "value": "application/json"
        }
      ],
      "parameters": [],
      "authentication": {},
      "body": {
        "mimeType": "application/json",
        "text": "{\n  \"name\": \"Test Promotion (Updated)\",\n  \"threshold\": 5,\n  \"rewardValue\": 20,\n  \"isActive\": false\n}"
      },
      "settingStoreCookies": true,
      "settingSendCookies": true,
      "settingDisableRenderRequestBody": false,
      "settingEncodeUrl": true,
      "settingRebuildPath": true,
      "settingFollowRedirects": "global",
      "settingRepeatDelay": 0,
      "settingMaxRedirects": 0,
      "created": 0,
      "modified": 0
    },
    {
      "_id": "req_promotion-crud_05",
      "_type": "request",
      "parentId": "grp_promotion-crud",
      "name": "Delete Promotion",
      "method": "DELETE",
      "url": "{{baseUrl}}/api/promotion/{{deletePromotionId}}",
      "headers": [
        {
          "name": "Accept",
          "value": "application/json"
        }
      ],
      "parameters": [],
      "authentication": {},
      "body": {},
      "settingStoreCookies": true,
      "settingSendCookies": true,
      "settingDisableRenderRequestBody": false,
      "settingEncodeUrl": true,
      "settingRebuildPath": true,
      "settingFollowRedirects": "global",
      "settingRepeatDelay": 0,
      "settingMaxRedirects": 0,
      "created": 0,
      "modified": 0
    },
    {
      "_id": "req_promotion-crud_06",
      "_type": "request",
      "parentId": "grp_promotion-crud",
      "name": "Get Deleted Promotion (404)",
      "method": "GET",
      "url": "{{baseUrl}}/api/promotion/{{promotionId}}",
      "headers": [
        {
          "name": "Accept",
          "value": "application/json"
        }
      ],
      "parameters": [],
      "authentication": {},
      "body": {},
      "settingStoreCookies": true,
      "settingSendCookies": true,
      "settingDisableRenderRequestBody": false,
      "settingEncodeUrl": true,
      "settingRebuildPath": true,
      "settingFollowRedirects": "global",
      "settingRepeatDelay": 0,
      "settingMaxRedirects": 0,
      "created": 0,
      "modified": 0
    },
    {
      "_id": "req_promotion-crud_07",
      "_type": "request",
      "parentId": "grp_promotion-crud",
      "name": "Update Non-existent Promotion (404)",
      "method": "PUT",
      "url": "{{baseUrl}}/api/promotion/999999",
      "headers": [
        {
          "name": "Content-Type",
          "value": "application/json"
        },
        {
          "name": "Accept",
          "value": "application/json"
        }
      ],
      "parameters": [],
      "authentication": {},
      "body": {
        "mimeType": "application/json",
        "text": "{\n  \"name\": \"Ghost Promotion\"\n}\n"
      },
      "settingStoreCookies": true,
      "settingSendCookies": true,
      "settingDisableRenderRequestBody": false,
      "settingEncodeUrl": true,
      "settingRebuildPath": true,
      "settingFollowRedirects": "global",
      "settingRepeatDelay": 0,
      "settingMaxRedirects": 0,
      "created": 0,
      "modified": 0
    },
    {
      "_id": "req_promotion-crud_08",
      "_type": "request",
      "parentId": "grp_promotion-crud",
      "name": "Delete Non-existent Promotion (404)",
      "method": "DELETE",
      "url": "{{baseUrl}}/api/promotion/999999",
      "headers": [
        {
          "name": "Accept",
          "value": "application/json"
        }
      ],
      "parameters": [],
      "authentication": {},
      "body": {},
      "settingStoreCookies": true,
      "settingSendCookies": true,
      "settingDisableRenderRequestBody": false,
      "settingEncodeUrl": true,
      "settingRebuildPath": true,
      "settingFollowRedirects": "global",
      "settingRepeatDelay": 0,
      "settingMaxRedirects": 0,
      "created": 0,
      "modified": 0
    }
  ]
}
